main.py
bertho_toolkit/__init__.py
bertho_toolkit/env_manager.py
bertho_toolkit/file_manager.py
bertho_toolkit/terminal_logger.py
bertho_toolkit-1.0.0.dist-info/METADATA
bertho_toolkit-1.0.0.dist-info/WHEEL
bertho_toolkit-1.0.0.dist-info/top_level.txt
bertho_toolkit-1.0.0.dist-info/RECORD
