Metadata-Version: 2.4
Name: bertho-toolkit
Version: 1.0.0
Summary: Collection of utilities for logging, file management, and environment variable handling.
Home-page: https://github.com/bertho-toolkit/bertho-python-toolkit
Author: Matheus Bertho
Author-email: Matheus Bertho <matheus.berthot@gmail.com>
License: MIT
Keywords: toolkit,utilities,environment,files,logging,terminal
Requires-Python: >=3.8
